setup.py
pygments_github_lexers/__init__.py
pygments_github_lexers/github.py
pygments_github_lexers.egg-info/PKG-INFO
pygments_github_lexers.egg-info/SOURCES.txt
pygments_github_lexers.egg-info/dependency_links.txt
pygments_github_lexers.egg-info/entry_points.txt
pygments_github_lexers.egg-info/requires.txt
pygments_github_lexers.egg-info/top_level.txt