Metadata-Version: 1.1
Name: pygments-github-lexers
Version: 0.0.3
Summary: Pygments Github custom lexers.
Home-page: https://github.com/liluo/pygments-github-lexers
Author: Liluo
Author-email: i@liluo.org
License: BSD
Keywords: pygments github lexer
Platform: UNKNOWN
Classifier: Environment :: Plugins
Classifier: Intended Audience :: Developers
Classifier: License :: OSI Approved :: BSD License
Classifier: Operating System :: OS Independent
Classifier: Programming Language :: Python
Classifier: Programming Language :: Python :: 2
Classifier: Programming Language :: Python :: 3
Classifier: Topic :: Software Development :: Libraries :: Python Modules
